rest/__init__.py
rest/LOTR/__init__.py
the_one_sdk-0.1.0.dist-info/METADATA
the_one_sdk-0.1.0.dist-info/WHEEL
the_one_sdk-0.1.0.dist-info/top_level.txt
the_one_sdk-0.1.0.dist-info/RECORD
